aria2tui/__init__.py
aria2tui/__main__.py
aria2tui/aria2tui.py
aria2tui/aria2tui_app.py
aria2tui/data/config.toml
aria2tui/graphing/__init__.py
aria2tui/graphing/graph_utils.py
aria2tui/graphing/pane_files.py
aria2tui/graphing/pane_graph.py
aria2tui/graphing/pane_graph_progress.py
aria2tui/graphing/pane_pieces.py
aria2tui/graphing/speed_graph.py
aria2tui/graphing/speed_graph_plain_text.py
aria2tui/lib/__init__.py
aria2tui/lib/aria2c_wrapper.py
aria2tui/ui/__init__.py
aria2tui/ui/aria2_detailing.py
aria2tui/ui/aria2tui_form.py
aria2tui/ui/aria2tui_keys.py
aria2tui/ui/aria2tui_menu_options.py
aria2tui/utils/__init__.py
aria2tui/utils/aria2c_utils.py
aria2tui/utils/aria_adduri.py
aria2tui/utils/display_info.py
aria2tui/utils/logging_utils.py
aria2tui/utils/aria2c/__init__.py
aria2tui/utils/aria2c/_lambdas.py
aria2tui/utils/aria2c/core.py
aria2tui/utils/aria2c/downloads.py
aria2tui/utils/aria2c/files.py
aria2tui/utils/aria2c/format.py
aria2tui/utils/aria2c/options.py
aria2tui/utils/aria2c/rpc.py
aria2tui-0.1.13.0.data/data/~/.config/aria2tui/config.toml
aria2tui-0.1.13.0.dist-info/licenses/LICENSE.txt
aria2tui-0.1.13.0.dist-info/METADATA
aria2tui-0.1.13.0.dist-info/WHEEL
aria2tui-0.1.13.0.dist-info/entry_points.txt
aria2tui-0.1.13.0.dist-info/top_level.txt
aria2tui-0.1.13.0.dist-info/RECORD
