Metadata-Version: 2.4
Name: aria2tui
Version: 0.1.13.0
Summary: aria2tui: A TUI Frontend for the Aria2c Download Manager
Home-page: https://github.com/grimandgreedy/aria2tui
Author: Grim
Author-email: grimandgreedy@protonmail.com
Project-URL: Bug Tracker, https://github.com/grimandgreedy/aria2tui/issues
Keywords: aria2c aria2 downloader listpick tui python curses torrent metalink
Classifier: Programming Language :: Python :: 3
Classifier: License :: OSI Approved :: MIT License
Classifier: Operating System :: Unix
Requires-Python: >=3.9
License-File: LICENSE.txt
Requires-Dist: plotille
Requires-Dist: Requests
Requires-Dist: tabulate
Requires-Dist: toml
Requires-Dist: listpick==0.1.18.0
Requires-Dist: numpy
Dynamic: author
Dynamic: author-email
Dynamic: classifier
Dynamic: description
Dynamic: description-content-type
Dynamic: home-page
Dynamic: keywords
Dynamic: license-file
Dynamic: project-url
Dynamic: requires-dist
Dynamic: requires-python
Dynamic: summary
